hdu_api/__init__.py
hdu_api/__version__.py
hdu_api/_internal_utils.py
hdu_api/_pyDes.py
hdu_api/api.py
hdu_api/config.py
hdu_api/exceptions.py
hdu_api/models.py
hdu_api/sessions.py
hdu_api-0.1.0.dist-info/LICENSE
hdu_api-0.1.0.dist-info/METADATA
hdu_api-0.1.0.dist-info/WHEEL
hdu_api-0.1.0.dist-info/top_level.txt
hdu_api-0.1.0.dist-info/RECORD
